odoo/addons/l10n_es_aeat_mod303_print_copy_copy/README.rst
odoo/addons/l10n_es_aeat_mod303_print_copy_copy/__init__.py
odoo/addons/l10n_es_aeat_mod303_print_copy_copy/__manifest__.py
odoo/addons/l10n_es_aeat_mod303_print_copy_copy/i18n/es.po
odoo/addons/l10n_es_aeat_mod303_print_copy_copy/report/aeat_mod303.xml
odoo/addons/l10n_es_aeat_mod303_print_copy_copy/report/report_views.xml
odoo/addons/l10n_es_aeat_mod303_print_copy_copy/static/description/icon.png
odoo_addon_l10n_es_aeat_mod303_print_copy_copy-15.0.1.0.1.dist-info/METADATA
odoo_addon_l10n_es_aeat_mod303_print_copy_copy-15.0.1.0.1.dist-info/WHEEL
odoo_addon_l10n_es_aeat_mod303_print_copy_copy-15.0.1.0.1.dist-info/top_level.txt
odoo_addon_l10n_es_aeat_mod303_print_copy_copy-15.0.1.0.1.dist-info/RECORD
